{
  "view.menu": {
    "extends": "view.basic",
    "class": "APPbackofficeServicesViewsMenuView",
    "arguments": ["@handler.menu"],
    "tags": [
      { "name": "view" }
    ]
  },
  "view.notifications": {
    "extends": "view.basic",
    "class": "APPbackofficeServicesViewsNotificationsView",
    "arguments": ["@notifier"],
    "tags": [
      { "name": "view" }
    ]
  },
  "view.blocks": {
    "extends": "view.basic",
    "class": "APPbackofficeServicesViewsBlocksView",
    "arguments": ["@handler.block"],
    "tags": [
      { "name": "view" }
    ]
  }
}